{
    "zakladni-prehled.csv": "31.10.2021 08:07",
    "osoby.csv": "31.10.2021 07:41",
    "vyleceni.csv": "27.10.2021 08:09",
    "umrti.csv": "27.10.2021 08:10",
    "hospitalizace.csv": "31.10.2021 07:43",
    "nakazeni-vyleceni-umrti-testy.csv": "31.10.2021 08:07",
    "kraj-okres-nakazeni-vyleceni-umrti.csv": "31.10.2021 08:07",
    "orp.csv": "31.10.2021 07:43",
    "obce.csv": "31.10.2021 07:45",
    "mestske-casti.csv": "31.10.2021 07:48",
    "incidence-7-14-cr.csv": "31.10.2021 07:43",
    "incidence-7-14-kraje.csv": "31.10.2021 07:43",
    "incidence-7-14-okresy.csv": "31.10.2021 07:43",
    "testy-pcr-antigenni.csv": "31.10.2021 07:43",
    "kraj-okres-testy.csv": "31.10.2021 07:43",
    "prehled-odberovych-mist.csv": "31.10.2021 07:43",
    "ockovani.csv": "31.10.2021 07:48",
    "ockovaci-mista.csv": "31.10.2021 07:50",
    "prehled-ockovacich-mist.csv": "31.10.2021 07:58",
    "ockovani-spotreba.csv": "31.10.2021 07:58",
    "ockovani-distribuce.csv": "31.10.2021 07:59",
    "ockovani-distribuce-sklad.csv": "31.10.2021 07:59",
    "ockovani-registrace.csv": "31.10.2021 08:00",
    "ockovani-rezervace.csv": "31.10.2021 08:07",
    "ockovani-profese.csv": "31.10.2021 04:53",
    "ockovani-demografie.csv": "31.10.2021 07:57",
    "ockovani-geografie.csv": "31.10.2021 07:57",
    "ockovaci-zarizeni.csv": "31.10.2021 08:07",
    "ockovani-zakladni-prehled.csv": "31.10.2021 07:57",
    "prioritni-skupiny.csv": "11.08.2021 13:41",
    "pomucky.csv": "11.08.2021 13:41"
}